awscdk_components/__init__.py
awscdk_components/cognito/__init__.py
awscdk_components/cognito/cognito.py
awscdk_components/elb/__init__.py
awscdk_components/elb/alb_https.py
awscdk_components/elb/alb_utils.py
awscdk_components/tests/__init__.py
awscdk_components/tests/test_alb_https.py
awscdk_components/tests/test_alb_utils.py
awscdk_components/tests/test_cognito.py
awscdk_components/tests/unittest_utils.py
rbi_oss_awscdk_components_pkg-0.6.0.dist-info/LICENSE
rbi_oss_awscdk_components_pkg-0.6.0.dist-info/METADATA
rbi_oss_awscdk_components_pkg-0.6.0.dist-info/WHEEL
rbi_oss_awscdk_components_pkg-0.6.0.dist-info/top_level.txt
rbi_oss_awscdk_components_pkg-0.6.0.dist-info/RECORD
