Metadata-Version: 2.1
Name: rbi-oss-awscdk-components-pkg
Version: 0.6.0
Summary: A collection of AWS CDK constructs and utils written in python
Home-page: https://github.com/raiffeisenbankinternational/awscdk-components-py
Author: RBI OSS Initiative
Author-email: RBI-OSSINITIATIVE_Admins@rbinternational.com
License: UNKNOWN
Platform: UNKNOWN
Classifier: Development Status :: 4 - Beta
Classifier: Intended Audience :: Developers
Classifier: License :: OSI Approved :: Apache Software License
Classifier: Programming Language :: JavaScript
Classifier: Programming Language :: Python :: 3 :: Only
Classifier: Programming Language :: Python :: 3.6
Classifier: Programming Language :: Python :: 3.7
Classifier: Programming Language :: Python :: 3.8
Classifier: Typing :: Typed
Requires-Python: >=3.6
Requires-Dist: aws-cdk.core (>=1.72.0)
Requires-Dist: aws-cdk.aws-elasticloadbalancingv2 (>=1.72.0)
Requires-Dist: aws-cdk.aws-elasticloadbalancingv2-targets (>=1.72.0)
Requires-Dist: aws-cdk.aws-ec2 (>=1.72.0)
Requires-Dist: aws-cdk.aws-cognito (>=1.72.0)
Requires-Dist: aws-cdk.aws-lambda (>=1.72.0)
